barium_meal/__init__.py
barium_meal/barium_meal.py
barium_meal-0.0.10.dist-info/LICENSE.txt
barium_meal-0.0.10.dist-info/METADATA
barium_meal-0.0.10.dist-info/WHEEL
barium_meal-0.0.10.dist-info/top_level.txt
barium_meal-0.0.10.dist-info/RECORD
