Metadata-Version: 2.1
Name: barium-meal
Version: 0.0.10
Summary: Convenience wrapper for OpenTelemetry
Home-page: https://github.com/peckhamdata/barium-meal
Author: Peckham Data Centre
Author-email: chris@peckhamdata.com
License: MIT
Platform: UNKNOWN
Classifier: Programming Language :: Python :: 3
Classifier: License :: OSI Approved :: MIT License
Classifier: Operating System :: OS Independent
Requires-Python: >=3.6
Requires-Dist: pytest
Requires-Dist: flask
Requires-Dist: opentelemetry-exporter-jaeger
Requires-Dist: opentelemetry-api
Requires-Dist: opentelemetry-instrumentation-requests
Requires-Dist: opentelemetry-instrumentation-boto
Requires-Dist: opentelemetry-instrumentation-flask
